README.md
setup.py
highlight_cli/__init__.py
highlight_cli/main.py
highlight_cli.egg-info/PKG-INFO
highlight_cli.egg-info/SOURCES.txt
highlight_cli.egg-info/dependency_links.txt
highlight_cli.egg-info/entry_points.txt
highlight_cli.egg-info/requires.txt
highlight_cli.egg-info/top_level.txt