Metadata-Version: 2.1
Name: highlight-cli
Version: 1.1.0
Summary: Highlight text within input.
Home-page: https://github.com/talwrii/highlight-cli
Author: @readwithai
Author-email: talwrii@gmail.com
License: MIT
Keywords: highlight,cli,command-line
